everlastly/__init__.py
everlastly/everlastly.py
everlastly/tests.py
everlastly-1.0.6.dist-info/DESCRIPTION.rst
everlastly-1.0.6.dist-info/METADATA
everlastly-1.0.6.dist-info/RECORD
everlastly-1.0.6.dist-info/WHEEL
everlastly-1.0.6.dist-info/metadata.json
everlastly-1.0.6.dist-info/top_level.txt
